rwth_jupyter_rdfify/__init__.py
rwth_jupyter_rdfify/graph.py
rwth_jupyter_rdfify/graph_manager.py
rwth_jupyter_rdfify/jupyter_rdf.py
rwth_jupyter_rdfify/log.py
rwth_jupyter_rdfify/persistence.py
rwth_jupyter_rdfify/prov.py
rwth_jupyter_rdfify/rdf_module.py
rwth_jupyter_rdfify/serialization.py
rwth_jupyter_rdfify/shaclvalidation.py
rwth_jupyter_rdfify/sparql.py
rwth_jupyter_rdfify/table.py
rwth_jupyter_rdfify/util.py
rwth_jupyter_rdfify-1.6.dist-info/licenses/LICENSE
rwth_jupyter_rdfify-1.6.dist-info/METADATA
rwth_jupyter_rdfify-1.6.dist-info/WHEEL
rwth_jupyter_rdfify-1.6.dist-info/top_level.txt
rwth_jupyter_rdfify-1.6.dist-info/RECORD
