Metadata-Version: 2.4
Name: rwth-jupyter-rdfify
Version: 1.6
Summary: IPython Extension for semantic web technology support (Turtle, SPARQL, etc.)
Author: Lars Pieschel, Md. Rezaul Karim
Author-email: Laurenz Neumann <laurenz.neumann@dbis.rwth-aachen.de>
Project-URL: Homepage, https://github.com/SemWebNotebooks/Jupyter-RDFify
Classifier: Programming Language :: Python :: 3
Classifier: License :: OSI Approved :: MIT License
Classifier: Operating System :: OS Independent
Classifier: Framework :: IPython
Requires-Python: >=3.13
License-File: LICENSE
Requires-Dist: rdflib~=6.0
Requires-Dist: ipython>=7.0.0
Requires-Dist: graphviz
Requires-Dist: sparqlwrapper>=1.8.5
Requires-Dist: sparqlslurper~=0.4
Requires-Dist: PyShEx
Requires-Dist: owlrl
Requires-Dist: pyshacl>=0.24.0
Requires-Dist: prov[rdf]
Dynamic: license-file
